zds_to_grav/__init__.py
zds_to_grav/zds_to_grav.py
zds_to_grav-1.0.2.dist-info/LICENSE
zds_to_grav-1.0.2.dist-info/METADATA
zds_to_grav-1.0.2.dist-info/WHEEL
zds_to_grav-1.0.2.dist-info/entry_points.txt
zds_to_grav-1.0.2.dist-info/top_level.txt
zds_to_grav-1.0.2.dist-info/RECORD
