Metadata-Version: 2.1
Name: zds-to-grav
Version: 1.0.2
Summary: Converts Zeste de Savoir articles to Grav
Home-page: http://github.com/AmauryCarrade/zds-to-grav
Author: Amaury Carrade
Author-email: amaury@carrade.eu
License: CeCILL-B
Platform: UNKNOWN
Classifier: Environment :: Console
Classifier: Programming Language :: Python
Classifier: Development Status :: 4 - Beta
Classifier: License :: OSI Approved
Classifier: Natural Language :: English
Classifier: Operating System :: OS Independent
Classifier: Programming Language :: Python :: 3.6
Classifier: Topic :: Text Processing
Classifier: Topic :: Utilities
Requires-Dist: click (>=6)
Requires-Dist: requests
Requires-Dist: path.py (>=2.19)
Requires-Dist: bs4
Requires-Dist: awesome-slugify
Requires-Dist: pyyaml
